[
  {
    "run_id": "build_a_distributed_weather_monitoring_s_20260221_141145",
    "timestamp": 1771679550.390026,
    "python_files": 2,
    "yaml_files": 7,
    "lines_of_code": 65,
    "total_functions": 5,
    "async_functions": 5,
    "imports": 10,
    "score": 57.5
  },
  {
    "run_id": "build_a_distributed_weather_monitoring_s_20260221_142630",
    "timestamp": 1771680433.7225106,
    "python_files": 2,
    "yaml_files": 9,
    "lines_of_code": 69,
    "total_functions": 6,
    "async_functions": 6,
    "imports": 10,
    "score": 64.5
  },
  {
    "run_id": ".git",
    "timestamp": 1771681643.0375612,
    "python_files": 0,
    "yaml_files": 0,
    "lines_of_code": 0,
    "total_functions": 0,
    "async_functions": 0,
    "imports": 0,
    "score": 0.0
  },
  {
    "run_id": ".git",
    "timestamp": 1771682849.7633264,
    "python_files": 0,
    "yaml_files": 0,
    "lines_of_code": 0,
    "total_functions": 0,
    "async_functions": 0,
    "imports": 0,
    "score": 0.0
  },
  {
    "run_id": ".git",
    "timestamp": 1771682855.870989,
    "python_files": 0,
    "yaml_files": 0,
    "lines_of_code": 0,
    "total_functions": 0,
    "async_functions": 0,
    "imports": 0,
    "score": 0.0
  },
  {
    "run_id": "build_a_code_review_pipeline_with_analys_20260221_152319",
    "timestamp": 1771684063.8990455,
    "python_files": 2,
    "yaml_files": 8,
    "lines_of_code": 64,
    "total_functions": 5,
    "async_functions": 5,
    "imports": 10,
    "score": 57.0
  },
  {
    "run_id": ".git",
    "timestamp": 1771685265.8700526,
    "python_files": 0,
    "yaml_files": 0,
    "lines_of_code": 0,
    "total_functions": 0,
    "async_functions": 0,
    "imports": 0,
    "score": 0.0
  },
  {
    "run_id": ".git",
    "timestamp": 1771685273.467667,
    "python_files": 0,
    "yaml_files": 0,
    "lines_of_code": 0,
    "total_functions": 0,
    "async_functions": 0,
    "imports": 0,
    "score": 0.0
  },
  {
    "run_id": "build_a_code_review_pipeline_with_analys_20260221_155845",
    "timestamp": 1771686472.5545568,
    "python_files": 6,
    "yaml_files": 5,
    "lines_of_code": 141,
    "total_functions": 8,
    "async_functions": 7,
    "imports": 25,
    "score": 58.5
  },
  {
    "run_id": ".git",
    "timestamp": 1771686481.587926,
    "python_files": 0,
    "yaml_files": 0,
    "lines_of_code": 0,
    "total_functions": 0,
    "async_functions": 0,
    "imports": 0,
    "score": 0.0
  },
  {
    "run_id": ".git",
    "timestamp": 1771687689.6607091,
    "python_files": 0,
    "yaml_files": 0,
    "lines_of_code": 0,
    "total_functions": 0,
    "async_functions": 0,
    "imports": 0,
    "score": 0.0
  },
  {
    "run_id": "build_a_customer_support_system_with_tri_20260221_164441",
    "timestamp": 1771688898.598825,
    "python_files": 5,
    "yaml_files": 5,
    "lines_of_code": 123,
    "total_functions": 6,
    "async_functions": 5,
    "imports": 20,
    "score": 49.6
  },
  {
    "run_id": ".git",
    "timestamp": 1771690106.6139917,
    "python_files": 0,
    "yaml_files": 0,
    "lines_of_code": 0,
    "total_functions": 0,
    "async_functions": 0,
    "imports": 0,
    "score": 0.0
  },
  {
    "run_id": ".git",
    "timestamp": 1771691314.5199223,
    "python_files": 0,
    "yaml_files": 0,
    "lines_of_code": 0,
    "total_functions": 0,
    "async_functions": 0,
    "imports": 0,
    "score": 0.0
  },
  {
    "run_id": "build_a_distributed_weather_monitoring_s_20260221_174334",
    "timestamp": 1771692525.0244615,
    "python_files": 2,
    "yaml_files": 8,
    "lines_of_code": 277,
    "total_functions": 26,
    "async_functions": 26,
    "imports": 10,
    "score": 268.5
  },
  {
    "run_id": ".git",
    "timestamp": 1771693735.1541784,
    "python_files": 0,
    "yaml_files": 0,
    "lines_of_code": 0,
    "total_functions": 0,
    "async_functions": 0,
    "imports": 0,
    "score": 0.0
  },
  {
    "run_id": ".git",
    "timestamp": 1771694943.4539518,
    "python_files": 0,
    "yaml_files": 0,
    "lines_of_code": 0,
    "total_functions": 0,
    "async_functions": 0,
    "imports": 0,
    "score": 0.0
  },
  {
    "run_id": "build_an_agentic_learning_course_system__20260221_193640",
    "timestamp": 1771699023.5100458,
    "python_files": 2,
    "yaml_files": 9,
    "lines_of_code": 81,
    "total_functions": 3,
    "async_functions": 3,
    "imports": 10,
    "score": 55.5
  },
  {
    "run_id": ".git",
    "timestamp": 1771700238.9382458,
    "python_files": 0,
    "yaml_files": 0,
    "lines_of_code": 0,
    "total_functions": 0,
    "async_functions": 0,
    "imports": 0,
    "score": 0.0
  },
  {
    "run_id": ".git",
    "timestamp": 1771701454.178574,
    "python_files": 0,
    "yaml_files": 0,
    "lines_of_code": 0,
    "total_functions": 0,
    "async_functions": 0,
    "imports": 0,
    "score": 0.0
  },
  {
    "run_id": "build_a_customer_support_system_with_tri_20260221_202649",
    "timestamp": 1771702674.244717,
    "python_files": 2,
    "yaml_files": 5,
    "lines_of_code": 68,
    "total_functions": 2,
    "async_functions": 2,
    "imports": 7,
    "score": 44.0
  },
  {
    "run_id": "build_a_real_time_stock_price_alert_syst_20260221_205303",
    "timestamp": 1771703882.977096,
    "python_files": 2,
    "yaml_files": 7,
    "lines_of_code": 76,
    "total_functions": 4,
    "async_functions": 4,
    "imports": 10,
    "score": 58.0
  },
  {
    "run_id": ".git",
    "timestamp": 1771705094.6289408,
    "python_files": 0,
    "yaml_files": 0,
    "lines_of_code": 0,
    "total_functions": 0,
    "async_functions": 0,
    "imports": 0,
    "score": 0.0
  },
  {
    "run_id": ".git",
    "timestamp": 1771706305.5135534,
    "python_files": 0,
    "yaml_files": 0,
    "lines_of_code": 0,
    "total_functions": 0,
    "async_functions": 0,
    "imports": 0,
    "score": 0.0
  },
  {
    "run_id": ".git",
    "timestamp": 1771707516.5357847,
    "python_files": 0,
    "yaml_files": 0,
    "lines_of_code": 0,
    "total_functions": 0,
    "async_functions": 0,
    "imports": 0,
    "score": 0.0
  },
  {
    "run_id": ".git",
    "timestamp": 1771708723.2363026,
    "python_files": 0,
    "yaml_files": 0,
    "lines_of_code": 0,
    "total_functions": 0,
    "async_functions": 0,
    "imports": 0,
    "score": 0.0
  },
  {
    "run_id": "build_a_weather_data_collection_and_repo_20260221_223304",
    "timestamp": 1771709935.310732,
    "python_files": 2,
    "yaml_files": 6,
    "lines_of_code": 196,
    "total_functions": 14,
    "async_functions": 14,
    "imports": 14,
    "score": 168.0
  },
  {
    "run_id": ".git",
    "timestamp": 1771711149.7940683,
    "python_files": 0,
    "yaml_files": 0,
    "lines_of_code": 0,
    "total_functions": 0,
    "async_functions": 0,
    "imports": 0,
    "score": 0.0
  },
  {
    "run_id": ".git",
    "timestamp": 1771712354.9253306,
    "python_files": 0,
    "yaml_files": 0,
    "lines_of_code": 0,
    "total_functions": 0,
    "async_functions": 0,
    "imports": 0,
    "score": 0.0
  },
  {
    "run_id": ".git",
    "timestamp": 1771714331.6091921,
    "python_files": 0,
    "yaml_files": 0,
    "lines_of_code": 0,
    "total_functions": 0,
    "async_functions": 0,
    "imports": 0,
    "score": 0.0
  },
  {
    "run_id": "build_a_customer_support_system_with_tri_20260222_000850",
    "timestamp": 1771715539.1399908,
    "python_files": 2,
    "yaml_files": 5,
    "lines_of_code": 191,
    "total_functions": 14,
    "async_functions": 14,
    "imports": 14,
    "score": 165.5
  },
  {
    "run_id": ".git",
    "timestamp": 1771716746.0677965,
    "python_files": 0,
    "yaml_files": 0,
    "lines_of_code": 0,
    "total_functions": 0,
    "async_functions": 0,
    "imports": 0,
    "score": 0.0
  },
  {
    "run_id": "build_an_agentic_learning_course_system__20260222_005229",
    "timestamp": 1771717964.0531116,
    "python_files": 2,
    "yaml_files": 9,
    "lines_of_code": 198,
    "total_functions": 13,
    "async_functions": 13,
    "imports": 14,
    "score": 164.0
  },
  {
    "run_id": "build_an_agentic_learning_course_system__20260222_005229",
    "timestamp": 1771717995.672333,
    "python_files": 2,
    "yaml_files": 9,
    "lines_of_code": 198,
    "total_functions": 13,
    "async_functions": 13,
    "imports": 14,
    "score": 164.0
  },
  {
    "run_id": ".git",
    "timestamp": 1771719175.6809788,
    "python_files": 0,
    "yaml_files": 0,
    "lines_of_code": 0,
    "total_functions": 0,
    "async_functions": 0,
    "imports": 0,
    "score": 0.0
  },
  {
    "run_id": ".git",
    "timestamp": 1771719203.569725,
    "python_files": 0,
    "yaml_files": 0,
    "lines_of_code": 0,
    "total_functions": 0,
    "async_functions": 0,
    "imports": 0,
    "score": 0.0
  }
]